[ 
  { 
    "name": "Academy Rector.png",
    "price": 1000000000
  }, 
  { 
    "name": "Adarkar Wastes.png",
    "price": 1000000000
  }, 
  { 
    "name": "Bitterblossom.png",
    "price": 1000000000
  }, 
  { 
    "name": "Brushland.png",
    "price": 1000000000
  }, 
  { 
    "name": "Cavern of Souls.png",
    "price": 1000000000
  }, 
  { 
    "name": "Caves of Koilos.png",
    "price": 1000000000
  }, 
  { 
    "name": "Chaos Orb.png",
    "price": 1000000000
  }, 
  { 
    "name": "Conservator.png",
    "price": 1000000000
  }, 
  { 
    "name": "Contract from Below.png",
    "price": 1000000000
  }, 
  { 
    "name": "Drana, Liberator of Malakir.png",
    "price": 1000000000
  }, 
  { 
    "name": "Ethereal Haze.png",
    "price": 1000000000
  }, 
  { 
    "name": "Ironclaw Orcs.png",
    "price": 1000000000
  }, 
  { 
    "name": "Jace, Memory Adept.png",
    "price": 1000000000
  }, 
  { 
    "name": "Kormus Bell.png",
    "price": 1000000000
  }, 
  { 
    "name": "Lightning Helix.png",
    "price": 1000000000
  }, 
  { 
    "name": "Llanowar Elves.png",
    "price": 1000000000
  }, 
  { 
    "name": "Mana Confluence.png",
    "price": 1000000000
  }, 
  { 
    "name": "Natural Selection.png",
    "price": 1000000000
  }, 
  { 
    "name": "Nevinyrral's Disk.png",
    "price": 1000000000
  }, 
  { 
    "name": "Noble Hierarch.png",
    "price": 1000000000
  }, 
  { 
    "name": "Paradox Engine.png",
    "price": 1000000000
  }, 
  { 
    "name": "Planar Bridge.png",
    "price": 1000000000
  }, 
  { 
    "name": "Primordial Hydra.png",
    "price": 1000000000
  }, 
  { 
    "name": "Raging Ravine.png",
    "price": 1000000000
  }, 
  { 
    "name": "Raging River.png",
    "price": 1000000000
  }, 
  { 
    "name": "Scrubland.png",
    "price": 1000000000
  }, 
  { 
    "name": "Solemn Simulacrum.png",
    "price": 1000000000
  }, 
  { 
    "name": "Swiftfoot Boots.png",
    "price": 1000000000
  }, 
  { 
    "name": "Tireless Tracker.png",
    "price": 1000000000
  }, 
  { 
    "name": "Trinisphere.png",
    "price": 1000000000
  }, 
  { 
    "name": "Ulamog, the Ceaseless Hunger.png",
    "price": 1000000000
  }, 
  { 
    "name": "Vampiric Tutor.png",
    "price": 1000000000
  }, 
  { 
  "name": "Windswept Heath.png",
  "price": 1000000000
  }
]